MANIFEST.in
README.txt
sebastien-retro-3b7ed0e.tar.gz
setup.cfg
setup.py
resmoni/CpuMonitor.py
resmoni/GetPostedFile.py
resmoni/LocalServer.py
resmoni/MemoryMonitor.py
resmoni/UsageDB.py
resmoni/UsageWebService.py
resmoni/__init__.py
resmoni/usage.py
resmoni/util.py
resmoni/version.py
resmonitor.egg-info/PKG-INFO
resmonitor.egg-info/SOURCES.txt
resmonitor.egg-info/dependency_links.txt
resmonitor.egg-info/entry_points.txt
resmonitor.egg-info/requires.txt
resmonitor.egg-info/top_level.txt