Metadata-Version: 1.0
Name: resmonitor
Version: 0.1.0
Summary: A resource monitoring : CPU and Memory monitor webservice
Home-page: UNKNOWN
Author: Francis Pieraut
Author-email: fpieraut@gmail.com
License: AGPL v3 or later
Platform: UNKNOWN
